{
  "2": {
    "street/court (plaza)": {
      "absolute": 14734,
      "percentage": 0.34
    },
    "building/school/dormitory (home) building": {
      "absolute": 25436,
      "percentage": 0.59
    },
    "green space": {
      "absolute": 960,
      "percentage": 0.02
    },
    "playground": {
      "absolute": 1318,
      "percentage": 0.03
    },
    "unknown": {
      "absolute": 321,
      "percentage": 0.01
    },
    "sports field": {
      "absolute": 1,
      "percentage": 0.0
    },
    "special facility": {
      "absolute": 56,
      "percentage": 0.0
    },
    "cemetery": {
      "absolute": 2,
      "percentage": 0.0
    },
    "allotment garden": {
      "absolute": 17,
      "percentage": 0.0
    },
    "biotope area": {
      "absolute": 3,
      "percentage": 0.0
    }
  },
  "0": {
    "building/school/dormitory (home) building": {
      "absolute": 9807,
      "percentage": 0.85
    },
    "street/court (plaza)": {
      "absolute": 990,
      "percentage": 0.09
    },
    "playground": {
      "absolute": 457,
      "percentage": 0.04
    },
    "green space": {
      "absolute": 128,
      "percentage": 0.01
    },
    "sports field": {
      "absolute": 1,
      "percentage": 0.0
    },
    "allotment garden": {
      "absolute": 1,
      "percentage": 0.0
    },
    "unknown": {
      "absolute": 170,
      "percentage": 0.01
    }
  },
  "1": {
    "building/school/dormitory (home) building": {
      "absolute": 35323,
      "percentage": 0.76
    },
    "street/court (plaza)": {
      "absolute": 9044,
      "percentage": 0.19
    },
    "green space": {
      "absolute": 618,
      "percentage": 0.01
    },
    "allotment garden": {
      "absolute": 21,
      "percentage": 0.0
    },
    "playground": {
      "absolute": 1031,
      "percentage": 0.02
    },
    "special facility": {
      "absolute": 3,
      "percentage": 0.0
    },
    "cemetery": {
      "absolute": 5,
      "percentage": 0.0
    },
    "unknown": {
      "absolute": 407,
      "percentage": 0.01
    }
  },
  "unknown": {
    "street/court (plaza)": {
      "absolute": 352,
      "percentage": 0.01
    },
    "building/school/dormitory (home) building": {
      "absolute": 43997,
      "percentage": 0.89
    },
    "green space": {
      "absolute": 26,
      "percentage": 0.0
    },
    "playground": {
      "absolute": 18,
      "percentage": 0.0
    },
    "unknown": {
      "absolute": 5017,
      "percentage": 0.1
    }
  }
}