{
  "Kalk": {
    "absolute": 13083,
    "percentage": 0.09
  },
  "Mülheim": {
    "absolute": 16844,
    "percentage": 0.12
  },
  "Innenstadt": {
    "absolute": 19002,
    "percentage": 0.13
  },
  "Porz": {
    "absolute": 11360,
    "percentage": 0.08
  },
  "Nippes": {
    "absolute": 15883,
    "percentage": 0.11
  },
  "unknown": {
    "absolute": 308,
    "percentage": 0.0
  },
  "Lindenthal": {
    "absolute": 23826,
    "percentage": 0.16
  },
  "Rodenkirchen": {
    "absolute": 14576,
    "percentage": 0.1
  },
  "Ehrenfeld": {
    "absolute": 14584,
    "percentage": 0.1
  },
  "Chorweiler": {
    "absolute": 16502,
    "percentage": 0.11
  }
}