{
  "street/court (plaza)": {
    "Kalk": {
      "absolute": 2064,
      "percentage": 0.08
    },
    "Mülheim": {
      "absolute": 2273,
      "percentage": 0.09
    },
    "Porz": {
      "absolute": 1749,
      "percentage": 0.07
    },
    "Innenstadt": {
      "absolute": 3895,
      "percentage": 0.16
    },
    "Nippes": {
      "absolute": 3091,
      "percentage": 0.12
    },
    "Lindenthal": {
      "absolute": 5197,
      "percentage": 0.21
    },
    "Rodenkirchen": {
      "absolute": 1988,
      "percentage": 0.08
    },
    "Ehrenfeld": {
      "absolute": 2705,
      "percentage": 0.11
    },
    "Chorweiler": {
      "absolute": 2038,
      "percentage": 0.08
    }
  },
  "building/school/dormitory (home) building": {
    "Mülheim": {
      "absolute": 12572,
      "percentage": 0.11
    },
    "Kalk": {
      "absolute": 10372,
      "percentage": 0.09
    },
    "Innenstadt": {
      "absolute": 13679,
      "percentage": 0.12
    },
    "Porz": {
      "absolute": 8998,
      "percentage": 0.08
    },
    "Nippes": {
      "absolute": 11497,
      "percentage": 0.1
    },
    "Lindenthal": {
      "absolute": 17349,
      "percentage": 0.16
    },
    "Rodenkirchen": {
      "absolute": 11655,
      "percentage": 0.11
    },
    "Ehrenfeld": {
      "absolute": 10724,
      "percentage": 0.1
    },
    "Chorweiler": {
      "absolute": 13871,
      "percentage": 0.13
    }
  },
  "green space": {
    "Mülheim": {
      "absolute": 259,
      "percentage": 0.15
    },
    "Kalk": {
      "absolute": 57,
      "percentage": 0.03
    },
    "Innenstadt": {
      "absolute": 412,
      "percentage": 0.24
    },
    "Lindenthal": {
      "absolute": 266,
      "percentage": 0.16
    },
    "Rodenkirchen": {
      "absolute": 57,
      "percentage": 0.03
    },
    "Ehrenfeld": {
      "absolute": 61,
      "percentage": 0.04
    },
    "Nippes": {
      "absolute": 347,
      "percentage": 0.2
    },
    "Chorweiler": {
      "absolute": 119,
      "percentage": 0.07
    },
    "Porz": {
      "absolute": 131,
      "percentage": 0.08
    }
  },
  "allotment garden": {
    "Mülheim": {
      "absolute": 1,
      "percentage": 0.03
    },
    "Innenstadt": {
      "absolute": 29,
      "percentage": 0.78
    },
    "Nippes": {
      "absolute": 7,
      "percentage": 0.19
    }
  },
  "playground": {
    "Kalk": {
      "absolute": 181,
      "percentage": 0.07
    },
    "Innenstadt": {
      "absolute": 547,
      "percentage": 0.2
    },
    "Lindenthal": {
      "absolute": 547,
      "percentage": 0.2
    },
    "Rodenkirchen": {
      "absolute": 488,
      "percentage": 0.18
    },
    "Ehrenfeld": {
      "absolute": 579,
      "percentage": 0.21
    },
    "Nippes": {
      "absolute": 254,
      "percentage": 0.09
    },
    "Chorweiler": {
      "absolute": 37,
      "percentage": 0.01
    },
    "Porz": {
      "absolute": 53,
      "percentage": 0.02
    },
    "Mülheim": {
      "absolute": 36,
      "percentage": 0.01
    }
  },
  "unknown": {
    "Lindenthal": {
      "absolute": 464,
      "percentage": 0.09
    },
    "Innenstadt": {
      "absolute": 440,
      "percentage": 0.08
    },
    "Mülheim": {
      "absolute": 1703,
      "percentage": 0.32
    },
    "Nippes": {
      "absolute": 682,
      "percentage": 0.13
    },
    "Porz": {
      "absolute": 371,
      "percentage": 0.07
    },
    "Chorweiler": {
      "absolute": 437,
      "percentage": 0.08
    },
    "Ehrenfeld": {
      "absolute": 513,
      "percentage": 0.09
    },
    "Kalk": {
      "absolute": 407,
      "percentage": 0.08
    },
    "Rodenkirchen": {
      "absolute": 388,
      "percentage": 0.07
    }
  },
  "sports field": {
    "Ehrenfeld": {
      "absolute": 2,
      "percentage": 1.0
    }
  },
  "special facility": {
    "Nippes": {
      "absolute": 4,
      "percentage": 0.07
    },
    "Porz": {
      "absolute": 55,
      "percentage": 0.93
    }
  },
  "cemetery": {
    "Kalk": {
      "absolute": 2,
      "percentage": 0.33
    },
    "Nippes": {
      "absolute": 1,
      "percentage": 0.17
    },
    "Lindenthal": {
      "absolute": 3,
      "percentage": 0.5
    }
  },
  "biotope area": {
    "Porz": {
      "absolute": 3,
      "percentage": 1.0
    }
  }
}